Metadata-Version: 2.4
Name: clovyr-workspace-mcp
Version: 1.8.2.post1
Summary: Comprehensive, highly performant Google Workspace Streamable HTTP & SSE MCP Server for Calendar, Gmail, Docs, Sheets, Slides & Drive
Author-email: Taylor Wilsdon <taylor@taylorwilsdon.com>
License: MIT
Project-URL: Homepage, https://workspacemcp.com
Project-URL: Repository, https://github.com/taylorwilsdon/google_workspace_mcp
Project-URL: Documentation, https://github.com/taylorwilsdon/google_workspace_mcp#readme
Project-URL: Issues, https://github.com/taylorwilsdon/google_workspace_mcp/issues
Project-URL: Changelog, https://github.com/taylorwilsdon/google_workspace_mcp/releases
Keywords: mcp,google,workspace,llm,ai,claude,model,context,protocol,server
Classifier: Development Status :: 4 - Beta
Classifier: Environment :: Console
Classifier: Intended Audience :: Developers
Classifier: License :: OSI Approved :: MIT License
Classifier: Natural Language :: English
Classifier: Operating System :: OS Independent
Classifier: Programming Language :: Python
Classifier: Programming Language :: Python :: 3 :: Only
Classifier: Programming Language :: Python :: 3.11
Classifier: Programming Language :: Python :: 3.12
Classifier: Topic :: Internet :: WWW/HTTP :: Dynamic Content
Classifier: Topic :: Internet :: WWW/HTTP :: HTTP Servers
Classifier: Topic :: Software Development :: Libraries :: Application Frameworks
Classifier: Topic :: Communications :: Chat
Classifier: Topic :: Office/Business
Classifier: Topic :: Scientific/Engineering :: Artificial Intelligence
Classifier: Typing :: Typed
Requires-Python: >=3.10
License-File: LICENSE
Requires-Dist: fastapi>=0.115.12
Requires-Dist: fastmcp>=2.14.4
Requires-Dist: google-api-python-client>=2.168.0
Requires-Dist: google-auth-httplib2>=0.2.0
Requires-Dist: google-auth-oauthlib>=1.2.2
Requires-Dist: httpx>=0.28.1
Requires-Dist: py-key-value-aio>=0.3.0
Requires-Dist: pyjwt>=2.10.1
Requires-Dist: python-dotenv>=1.1.0
Requires-Dist: pyyaml>=6.0.2
Requires-Dist: cryptography>=45.0.0
Provides-Extra: valkey
Requires-Dist: py-key-value-aio[valkey]>=0.3.0; extra == "valkey"
Provides-Extra: test
Requires-Dist: pytest>=8.3.0; extra == "test"
Requires-Dist: pytest-asyncio>=0.23.0; extra == "test"
Requires-Dist: requests>=2.32.3; extra == "test"
Provides-Extra: release
Requires-Dist: tomlkit>=0.13.3; extra == "release"
Requires-Dist: twine>=5.0.0; extra == "release"
Provides-Extra: dev
Requires-Dist: pytest>=8.3.0; extra == "dev"
Requires-Dist: pytest-asyncio>=0.23.0; extra == "dev"
Requires-Dist: requests>=2.32.3; extra == "dev"
Requires-Dist: ruff>=0.12.4; extra == "dev"
Requires-Dist: tomlkit>=0.13.3; extra == "dev"
Requires-Dist: twine>=5.0.0; extra == "dev"
Dynamic: license-file
